sqlalchemy_sybase/__init__.py
sqlalchemy_sybase/base.py
sqlalchemy_sybase/pyodbc.py
sqlalchemy_sybase/requirements.py
sqlalchemy_sybase-2.0.0.dist-info/LICENSE
sqlalchemy_sybase-2.0.0.dist-info/METADATA
sqlalchemy_sybase-2.0.0.dist-info/WHEEL
sqlalchemy_sybase-2.0.0.dist-info/entry_points.txt
sqlalchemy_sybase-2.0.0.dist-info/top_level.txt
sqlalchemy_sybase-2.0.0.dist-info/RECORD
