Metadata-Version: 2.1
Name: sqlalchemy-sybase
Version: 2.0.0
Summary: SAP ASE (Sybase) for SQLAlchemy
Home-page: https://github.com/gordthompson/sqlalchemy-sybase
Author: Gord Thompson
Author-email: gord@gordthompson.com
License: MIT
Project-URL: Documentation, https://github.com/gordthompson/sqlalchemy-sybase/wiki
Project-URL: Source, https://github.com/gordthompson/sqlalchemy-sybase
Project-URL: Tracker, https://github.com/gordthompson/sqlalchemy-sybase/issues
Keywords: ASE SAP SQLAlchemy Sybase
Classifier: Development Status :: 5 - Production/Stable
Classifier: Intended Audience :: Developers
Classifier: License :: OSI Approved :: MIT License
Classifier: Programming Language :: Python
Classifier: Programming Language :: Python :: 3
Classifier: Programming Language :: Python :: Implementation :: CPython
Classifier: Topic :: Database :: Front-Ends
Classifier: Operating System :: OS Independent
License-File: LICENSE
Requires-Dist: odbcinst
Requires-Dist: pyodbc
Requires-Dist: SQLAlchemy (>=2.0.0)
